pinterestsdk/__init__.py
pinterestsdk/api_client.py
pinterestsdk/api_response.py
pinterestsdk/configuration.py
pinterestsdk/exceptions.py
pinterestsdk/py.typed
pinterestsdk/rest.py
pinterestsdk/api/__init__.py
pinterestsdk/api/ad_accounts_api.py
pinterestsdk/api/ad_groups_api.py
pinterestsdk/api/ads_api.py
pinterestsdk/api/advanced_auction_api.py
pinterestsdk/api/audience_insights_api.py
pinterestsdk/api/audience_sharing_api.py
pinterestsdk/api/audiences_api.py
pinterestsdk/api/billing_api.py
pinterestsdk/api/boards_api.py
pinterestsdk/api/bulk_api.py
pinterestsdk/api/business_access_assets_api.py
pinterestsdk/api/business_access_invite_api.py
pinterestsdk/api/business_access_relationships_api.py
pinterestsdk/api/campaigns_api.py
pinterestsdk/api/catalog_feeds_api.py
pinterestsdk/api/catalog_items_api.py
pinterestsdk/api/catalog_product_groups_api.py
pinterestsdk/api/catalog_reports_api.py
pinterestsdk/api/catalogs_api.py
pinterestsdk/api/conversion_eqs_api.py
pinterestsdk/api/conversion_events_api.py
pinterestsdk/api/conversion_tags_api.py
pinterestsdk/api/conversions_api.py
pinterestsdk/api/customer_list_uploads_api.py
pinterestsdk/api/customer_lists_api.py
pinterestsdk/api/integrations_api.py
pinterestsdk/api/keywords_api.py
pinterestsdk/api/labels_api.py
pinterestsdk/api/lead_ads_api.py
pinterestsdk/api/lead_forms_api.py
pinterestsdk/api/leads_export_api.py
pinterestsdk/api/media_api.py
pinterestsdk/api/msot_events_api.py
pinterestsdk/api/notification_api.py
pinterestsdk/api/oauth_api.py
pinterestsdk/api/order_lines_api.py
pinterestsdk/api/pins_api.py
pinterestsdk/api/product_categories_api.py
pinterestsdk/api/product_group_promotions_api.py
pinterestsdk/api/promotions_api.py
pinterestsdk/api/resources_api.py
pinterestsdk/api/search_api.py
pinterestsdk/api/targeting_template_api.py
pinterestsdk/api/terms_api.py
pinterestsdk/api/terms_of_service_api.py
pinterestsdk/api/user_account_api.py
pinterestsdk/models/__init__.py
pinterestsdk/models/account.py
pinterestsdk-2.0.0.dist-info/METADATA
pinterestsdk-2.0.0.dist-info/WHEEL
pinterestsdk-2.0.0.dist-info/top_level.txt
pinterestsdk-2.0.0.dist-info/RECORD
