Metadata-Version: 2.4
Name: pinterestsdk
Version: 2.0.0
Summary: Pinterest REST API
Home-page: https://github.com/oapicf/pinterest-sdk
Author: OpenAPI Clients Factory
Author-email: OpenAPI Clients Factory <blah+oapicf@cliffano.com>
License: MIT
Project-URL: Repository, https://github.com/oapicf/pinterest-sdk
Keywords: OpenAPI,OpenAPI-Generator,Pinterest REST API
Requires-Python: >=3.9
Requires-Dist: urllib3<3.0.0,>=2.1.0
Requires-Dist: python-dateutil>=2.8.2
Requires-Dist: pydantic>=2
Requires-Dist: typing-extensions>=4.7.1
Dynamic: author
Dynamic: home-page
